solar_panel/__init__.py
solar_panel/core.py
solar_panel_inspection-0.1.dist-info/LICENSE
solar_panel_inspection-0.1.dist-info/METADATA
solar_panel_inspection-0.1.dist-info/WHEEL
solar_panel_inspection-0.1.dist-info/entry_points.txt
solar_panel_inspection-0.1.dist-info/top_level.txt
solar_panel_inspection-0.1.dist-info/RECORD
