Metadata-Version: 2.1
Name: solar-panel-inspection
Version: 0.1
Summary: A package to detect solar panels and save bounding box images.
Home-page: https://github.com/yourusername/solar-panel-inspection
Author: Mukesh Anand G
Author-email: ai.mukeshanandg@gmail.com
Classifier: Programming Language :: Python :: 3
Classifier: License :: OSI Approved :: MIT License
Classifier: Operating System :: OS Independent
Requires-Python: >=3.6
License-File: LICENSE
Requires-Dist: roboflow
Requires-Dist: Pillow
